README.md
setup.py
m2w64_zlib.egg-info/PKG-INFO
m2w64_zlib.egg-info/SOURCES.txt
m2w64_zlib.egg-info/dependency_links.txt
m2w64_zlib.egg-info/top_level.txt
m2w64zlib/__init__.py
m2w64zlib/_get_zlib_dll.py
m2w64zlib/compressor.py
m2w64zlib/tests.py